guppylang/__init__.py
guppylang/decorator.py
guppylang/defs.py
guppylang/experimental.py
guppylang/module.py
guppylang/py.typed
guppylang/emulator/__init__.py
guppylang/emulator/builder.py
guppylang/emulator/exceptions.py
guppylang/emulator/instance.py
guppylang/emulator/result.py
guppylang/emulator/state.py
guppylang/std/__init__.py
guppylang/std/angles.py
guppylang/std/array.py
guppylang/std/bool.py
guppylang/std/builtins.py
guppylang/std/debug.py
guppylang/std/either.py
guppylang/std/err.py
guppylang/std/futures.py
guppylang/std/iter.py
guppylang/std/lang.py
guppylang/std/list.py
guppylang/std/mem.py
guppylang/std/num.py
guppylang/std/option.py
guppylang/std/platform.py
guppylang/std/quantum_functional.py
guppylang/std/reflection.py
guppylang/std/string.py
guppylang/std/unsupported.py
guppylang/std/collections/__init__.py
guppylang/std/collections/priority_queue.py
guppylang/std/collections/stack.py
guppylang/std/qsystem/__init__.py
guppylang/std/qsystem/functional.py
guppylang/std/qsystem/random.py
guppylang/std/qsystem/utils.py
guppylang/std/qsystem/wasm.py
guppylang/std/quantum/__init__.py
guppylang/std/quantum/functional.py
guppylang-0.21.8.dist-info/METADATA
guppylang-0.21.8.dist-info/WHEEL
guppylang-0.21.8.dist-info/licenses/LICENCE
guppylang-0.21.8.dist-info/RECORD
