Metadata-Version: 2.4
Name: guppylang
Version: 0.21.8
Summary: Pythonic quantum-classical programming language
Project-URL: homepage, https://github.com/quantinuum/guppylang
Project-URL: repository, https://github.com/quantinuum/guppylang
Author-email: Mark Koch <mark.koch@quantinuum.com>, TKET development team <tket-support@quantinuum.com>
Maintainer-email: Mark Koch <mark.koch@quantinuum.com>, TKET development team <tket-support@quantinuum.com>
License:                                  Apache License
License-File: LICENCE
Classifier: Development Status :: 3 - Alpha
Classifier: Intended Audience :: Developers
Classifier: Intended Audience :: Science/Research
Classifier: License :: OSI Approved :: Apache Software License
Classifier: Programming Language :: Python :: 3
Classifier: Programming Language :: Python :: 3 :: Only
Classifier: Programming Language :: Python :: 3.10
Classifier: Programming Language :: Python :: 3.11
Classifier: Programming Language :: Python :: 3.12
Classifier: Programming Language :: Python :: 3.13
Classifier: Programming Language :: Python :: 3.14
Classifier: Topic :: Software Development :: Compilers
Requires-Python: <4,>=3.10
Requires-Dist: guppylang-internals~=0.27.0
Requires-Dist: numpy~=2.0
Requires-Dist: selene-hugr-qis-compiler~=0.2.9
Requires-Dist: selene-sim~=0.2.3
Requires-Dist: tqdm>=4.67.1
Requires-Dist: types-tqdm>=4.67.0.20250809
Provides-Extra: pytket
Requires-Dist: pytket>=1.34; extra == 'pytket'
Requires-Dist: tket>=0.12.7; extra == 'pytket'
